regoogle/__init__.py
regoogle/drive.py
regoogle-0.0.2.dist-info/METADATA
regoogle-0.0.2.dist-info/WHEEL
regoogle-0.0.2.dist-info/top_level.txt
regoogle-0.0.2.dist-info/RECORD
