Metadata-Version: 2.1
Name: regoogle
Version: 0.0.2
Summary: google api lib
Home-page: https://rescala.jp
Author: rv
Author-email: yo-maruya@rescala.jp
License: MIT
Project-URL: Bug Reports, https://github.com/rv-rescala/catsrequest/issues
Project-URL: Source, https://github.com/rv-rescala/catsrequest
Keywords: google api
Platform: UNKNOWN
Requires-Python: >=3.7
Requires-Dist: google-api-python-client
Requires-Dist: google-auth-httplib2
Requires-Dist: google-auth-oauthlib
Requires-Dist: oauth2client
